README.rst
setup.py
pyspaces/__init__.py
pyspaces/args_aliases.py
pyspaces/cli.py
pyspaces/cloning.py
pyspaces/libc.py
pyspaces/process.py
pyspaces/setns.py
pyspaces.egg-info/PKG-INFO
pyspaces.egg-info/SOURCES.txt
pyspaces.egg-info/dependency_links.txt
pyspaces.egg-info/entry_points.txt
pyspaces.egg-info/top_level.txt